twc/__init__.py
twc/__main__.py
twc/__version__.py
twc/api/__init__.py
twc/api/base.py
twc/api/client.py
twc/api/exceptions.py
twc/api/types.py
twc/apiwrap.py
twc/commands/__init__.py
twc/commands/account.py
twc/commands/apps.py
twc/commands/balancer.py
twc/commands/common.py
twc/commands/config.py
twc/commands/database.py
twc/commands/domain.py
twc/commands/firewall.py
twc/commands/floating_ip.py
twc/commands/image.py
twc/commands/kubernetes.py
twc/commands/project.py
twc/commands/server.py
twc/commands/ssh_key.py
twc/commands/storage.py
twc/commands/vpc.py
twc/fmt.py
twc/typerx.py
twc/utils.py
twc/vars.py
twc_cli-2.15.0.dist-info/METADATA
twc_cli-2.15.0.dist-info/WHEEL
twc_cli-2.15.0.dist-info/entry_points.txt
twc_cli-2.15.0.dist-info/licenses/COPYING
twc_cli-2.15.0.dist-info/RECORD
