Metadata-Version: 2.4
Name: twc-cli
Version: 2.15.0
Summary: Timeweb Cloud Command Line Interface.
License: MIT
License-File: COPYING
Author: ge
Author-email: dev@timeweb.cloud
Requires-Python: >=3.8.19,<4.0.0
Classifier: License :: OSI Approved :: MIT License
Classifier: Programming Language :: Python :: 3
Classifier: Programming Language :: Python :: 3.9
Classifier: Programming Language :: Python :: 3.10
Classifier: Programming Language :: Python :: 3.11
Classifier: Programming Language :: Python :: 3.12
Classifier: Programming Language :: Python :: 3.13
Classifier: Programming Language :: Python :: 3.14
Requires-Dist: click (<8.2.0)
Requires-Dist: colorama (>=0.4.6,<0.5.0)
Requires-Dist: pygments (>=2.18.0,<3.0.0)
Requires-Dist: pyyaml (>=6.0.1,<7.0.0)
Requires-Dist: requests (>=2.32.4,<3.0.0)
Requires-Dist: shellingham (>=1.5.4,<2.0.0)
Requires-Dist: toml (>=0.10.2,<0.11.0)
Requires-Dist: typer-slim (>=0.12.3,<0.13.0)
Project-URL: Homepage, https://github.com/timeweb-cloud/twc
Project-URL: Repository, https://github.com/timeweb-cloud/twc
